baai_modelhub/RSA.py
baai_modelhub/__init__.py
baai_modelhub/client.py
baai_modelhub/encryption.py
baai_modelhub-0.0.13.dist-info/METADATA
baai_modelhub-0.0.13.dist-info/WHEEL
baai_modelhub-0.0.13.dist-info/top_level.txt
baai_modelhub-0.0.13.dist-info/RECORD
